baseprompt/__init__.py
baseprompt/client.py
baseprompt/config.py
baseprompt-0.2.0.dist-info/METADATA
baseprompt-0.2.0.dist-info/WHEEL
baseprompt-0.2.0.dist-info/top_level.txt
baseprompt-0.2.0.dist-info/RECORD
